slackhooks/__init__.py
slackhooks/blocks/__init__.py
slackhooks/blocks/accessory.py
slackhooks/blocks/block.py
slackhooks/blocks/context.py
slackhooks/blocks/divider.py
slackhooks/blocks/element.py
slackhooks/blocks/section.py
slackhooks/blocks/text.py
slackhooks/client.py
slack_hooks-0.4.1.dist-info/LICENSE
slack_hooks-0.4.1.dist-info/WHEEL
slack_hooks-0.4.1.dist-info/METADATA
slack_hooks-0.4.1.dist-info/RECORD
