Metadata-Version: 2.1
Name: slack-hooks
Version: 0.4.1
Summary: Slack client for webhooks with Block Kit builder.
Home-page: https://github.com/fedecalendino/slack-hooks
License: MIT
Keywords: slack,webhooks,block kit
Author: Fede Calendino
Author-email: fede@calendino.com
Requires-Python: >=3.8,<4.0
Classifier: Intended Audience :: Developers
Classifier: License :: OSI Approved :: MIT License
Classifier: Programming Language :: Python :: 3
Classifier: Programming Language :: Python :: 3.10
Classifier: Programming Language :: Python :: 3.8
Classifier: Programming Language :: Python :: 3.9
Requires-Dist: requests (>=2.28.1,<3.0.0)
Project-URL: Documentation, https://github.com/fedecalendino/slack-hooks/blob/main/README.md
